{"uporabniki": [{"uporabnisko_ime": "test", "zasifrirano_geslo": "XXXolsegXXX", "stanje": {"stevilo_vseh_polj": 3, "polje_za_1": {"zaporedna_stevilka": 2, "mreza": [["0", "0", "0", "0", "0", "0", "0"], ["0", "0", "0", "0", "0", "0", "0"], ["0", "0", "0", "0", "0", "0", "0"], ["0", "0", "0", "M", "0", "0", "0"], ["0", "0", "M", "R", "0", "0", "0"], ["0", "0", "R", "M", "0", "0", "0"]], "na_vrsti": "igralec1"}, "polje_za_2": {"zaporedna_stevilka": 1, "mreza": [["0", "0", "0", "0", "0", "0", "0"], ["0", "0", "0", "0", "0", "0", "0"], ["0", "0", "0", "0", "0", "0", "0"], ["0", "0", "0", "0", "0", "0", "0"], ["0", "0", "0", "0", "0", "0", "0"], ["0", "0", "M", "0", "R", "R", "0"]], "na_vrsti": "igralec2"}, "statistika": {"stevilo_igranih_iger": 1, "stevilo_izgubljenih_iger": 1, "stevilo_zmaganih_iger": 0, "stevilo_neodlocenih_iger": 0, "seznam_koncanih": [0]}}}]}